pyvisainstrument/KeysightDAQ.py
pyvisainstrument/KeysightPSU.py
pyvisainstrument/KeysightVNA.py
pyvisainstrument/NumatoRelay.py
pyvisainstrument/VisaResource.py
pyvisainstrument/__init__.py
pyvisainstrument/testsuite/DummyDAQ.py
pyvisainstrument/testsuite/DummyPS.py
pyvisainstrument/testsuite/DummyTCPInstrument.py
pyvisainstrument/testsuite/DummyVNA.py
pyvisainstrument/testsuite/__init__.py
pyvisainstrument/utils.py
pyvisainstrument-1.5.2.dist-info/LICENSE.md
pyvisainstrument-1.5.2.dist-info/WHEEL
pyvisainstrument-1.5.2.dist-info/METADATA
pyvisainstrument-1.5.2.dist-info/RECORD
