Metadata-Version: 2.1
Name: pyvisainstrument
Version: 1.5.2
Summary: PyVisaInstrument provides boilerplate for various NI-VISA instruments.
Home-page: https://github.com/Samtec-ASH/pyvisainstrument
License: MIT
Author: Adam Page
Author-email: adam.page@samtec.com
Requires-Python: >=3.7,<4.0
Classifier: License :: OSI Approved :: MIT License
Classifier: Programming Language :: Python :: 3
Classifier: Programming Language :: Python :: 3.7
Classifier: Programming Language :: Python :: 3.8
Classifier: Programming Language :: Python :: 3.9
Classifier: Programming Language :: Python :: 3.10
Requires-Dist: PyVISA (>=1.11.3,<2.0.0)
Requires-Dist: PyVISA-py (>=0.5.2,<0.6.0)
Requires-Dist: numpy (>=1.20.1,<2.0.0)
Requires-Dist: pyserial (>=3.5,<4.0)
Requires-Dist: zeroconf (>=0.28.8,<0.29.0)
Project-URL: Repository, https://github.com/Samtec-ASH/pyvisainstrument
